securelink/__init__.py
securelink/api.py
securelink/config.py
securelink/sign.py
securelink-0.1.1.dist-info/LICENSE
securelink-0.1.1.dist-info/METADATA
securelink-0.1.1.dist-info/WHEEL
securelink-0.1.1.dist-info/RECORD
