Metadata-Version: 2.1
Name: securelink
Version: 0.1.1
Summary: A Python package to generate secure links for nginx.
License: MIT
Author: muslih_k_diy
Author-email: muslihk00@gmail.com
Requires-Python: >=3.9
Classifier: License :: OSI Approved :: MIT License
Classifier: Programming Language :: Python :: 3
Classifier: Programming Language :: Python :: 3.9
Classifier: Programming Language :: Python :: 3.10
Classifier: Programming Language :: Python :: 3.11
Classifier: Programming Language :: Python :: 3.12
Provides-Extra: api
Requires-Dist: fastapi (>=0.115.8,<0.116.0) ; extra == "api"
Requires-Dist: uvicorn (>=0.34.0,<0.35.0) ; extra == "api"
